mlservicewrapper/plugin/application_insights/__init__.py
mlservicewrapper_plugin_application_insights-0.2.0.dist-info/LICENSE
mlservicewrapper_plugin_application_insights-0.2.0.dist-info/METADATA
mlservicewrapper_plugin_application_insights-0.2.0.dist-info/WHEEL
mlservicewrapper_plugin_application_insights-0.2.0.dist-info/top_level.txt
mlservicewrapper_plugin_application_insights-0.2.0.dist-info/RECORD
